xlsxreporter/__init__.py
xlsxreporter/base.py
xlsxreporter/response.py
xlsxreporter/utils.py
xlsxreporter-0.1.4.dist-info/WHEEL
xlsxreporter-0.1.4.dist-info/METADATA
xlsxreporter-0.1.4.dist-info/RECORD
