Metadata-Version: 2.1
Name: xlsxreporter
Version: 0.1.4
Summary: A thin wrapper around xlsxwriter, to aid in generating row-by-row XLSX reports.
Home-page: UNKNOWN
License: UNKNOWN
Author: Jonas Myrlund
Author-email: myrlund@gmail.com
Requires-Python: >=3.6,<4.0
Classifier: Programming Language :: Python :: 3
Classifier: Programming Language :: Python :: 3.6
Classifier: Programming Language :: Python :: 3.7
Requires-Dist: xlsxwriter (>=1.1,<2.0)
